pygeometry2d/__init__.py
pygeometry2d/geometry.py
pygeometry2d-1.1.3.dist-info/licenses/LICENSE
pygeometry2d-1.1.3.dist-info/METADATA
pygeometry2d-1.1.3.dist-info/WHEEL
pygeometry2d-1.1.3.dist-info/top_level.txt
pygeometry2d-1.1.3.dist-info/RECORD
