Metadata-Version: 2.4
Name: pygeometry2d
Version: 1.1.3
Summary: 2D Geometry Library
Home-page: https://github.com/leonardopbatista/pygeometry2d
Author: Leonardo Pires Batista
Author-email: leonardopbatista98@gmail.com
License: MIT License
Project-URL: Documentation, https://pygeometry2d.readthedocs.io/
Project-URL: Source code, https://github.com/leonardopbatista/pygeometry2d
Project-URL: Download, https://github.com/leonardopbatista/pygeometry2d
Keywords: geometry 2d
License-File: LICENSE
Dynamic: author
Dynamic: author-email
Dynamic: description
Dynamic: description-content-type
Dynamic: home-page
Dynamic: keywords
Dynamic: license
Dynamic: license-file
Dynamic: project-url
Dynamic: summary
